cli/__init__.py
cli/input.py
cli/py.typed
cli/cli/__init__.py
cli/cli/entry_point.py
cli/commands/__init__.py
cli/commands/commands.py
cli/commands/open_.py
cli/commands/run.py
cli/commands/runner.py
cli/models/__init__.py
cli/models/models.py
cli/output/__init__.py
cli/output/console.py
cli/output/message.py
cli/output/progress.py
cli/output/rich.py
cli/output/status.py
powercli-0.3.7.dist-info/licenses/LICENSE
powercli-0.3.7.dist-info/METADATA
powercli-0.3.7.dist-info/WHEEL
powercli-0.3.7.dist-info/entry_points.txt
powercli-0.3.7.dist-info/top_level.txt
powercli-0.3.7.dist-info/RECORD
