Metadata-Version: 2.4
Name: powercli
Version: 0.3.7
Summary: High-level CLI interaction
Author-email: Quinten Roets <qdr2104@columbia.edu>
License-Expression: MIT
Project-URL: Source Code, https://github.com/quintenroets/cli
Requires-Python: <3.14,>=3.10
License-File: LICENSE
Requires-Dist: pexpect<5,>=4.9.0
Requires-Dist: rich<15,>=14.0.1
Provides-Extra: dev
Requires-Dist: hypothesis<7,>=6.97.1; extra == "dev"
Requires-Dist: package-dev-tools<1,>=0.7.1; extra == "dev"
Requires-Dist: package-dev-utils<1,>=0.1.6; extra == "dev"
Requires-Dist: superpathlib<3,>=2.0.2; extra == "dev"
Dynamic: license-file
